mdnice/__init__.py
mdnice/__version__.py
mdnice/image_uploaders.py
mdnice-0.0.1.dist-info/LICENSE
mdnice-0.0.1.dist-info/METADATA
mdnice-0.0.1.dist-info/WHEEL
mdnice-0.0.1.dist-info/RECORD
