Metadata-Version: 2.3
Name: mdnice
Version: 0.0.1
Summary: 将 Markdown 转换为微信公众号、知乎、稀土掘金支持的富文本格式
License: Apache-2.0
Keywords: markdown,converter,wechat,zhihu,juejin
Author: xiaoqiang
Author-email: xiaoqiangclub@hotmail.com
Requires-Python: >=3.8,<4.0
Classifier: License :: OSI Approved :: Apache Software License
Classifier: Programming Language :: Python :: 3
Classifier: Programming Language :: Python :: 3.8
Classifier: Programming Language :: Python :: 3.9
Classifier: Programming Language :: Python :: 3.10
Classifier: Programming Language :: Python :: 3.11
Classifier: Programming Language :: Python :: 3.12
Classifier: Programming Language :: Python :: 3.13
Requires-Dist: selenium (>=4.6.0,<5.0.0)
Project-URL: Homepage, https://github.com/xiaoqiangclub/mdnice
Project-URL: Repository, https://github.com/xiaoqiangclub/mdnice
